README.rst
setup.py
decimalize/__init__.py
decimalize/decimalize.py
decimalize/exceptions.py
decimalize/tests.py
decimalize.egg-info/PKG-INFO
decimalize.egg-info/SOURCES.txt
decimalize.egg-info/dependency_links.txt
decimalize.egg-info/top_level.txt