Metadata-Version: 1.1
Name: decimalize
Version: 1.0.1
Summary: decimalize is a package to convert radix flexibly.
Home-page: https://bitbucket.org/crohaco/decimalize
Author: crohaco
Author-email: crohaco.net@gmail.com
License: BSD License
Keywords: decimal,radix
Platform: UNKNOWN
Classifier: Environment :: Console
Classifier: Intended Audience :: Developers
Classifier: License :: OSI Approved :: BSD License
Classifier: Programming Language :: Python
Classifier: Topic :: Software Development
